{"userId":"62248bb18a6b8000163a8a5d","knowledgebaseId":"62248bb18a6b8000163a8a5d","name":"zyh","exportDate":"2022-03-16T13:20:15.105Z","exportVersion":1,"documentRemToExportId":"xeu4icH3N4Drt3JSR","docs":[{"key":["Document"],"owner":"62248bb18a6b8000163a8a5d","children":["WWor6M9ZxtgsAw69z","WLJKT5A8QqWKZTwAJ"],"subBlocks":["WLJKT5A8QqWKZTwAJ","WWor6M9ZxtgsAw69z"],"portalsIn":[],"createdAt":1646562244501,"n":1,"s":1646564640221,"u":1647341562448,"_id":"R7gQTq8r5vmqsJNeL","parent":null,"rcrt":"o","typeChildren":["QETxvfjqpsmEQmidA","ov6r9tR3sTkAafnNP","ou6pTRDXtsWPSaKYg","XTaHbWN6uuew5B4Kz","6oW8TrbdyFgyiR5xE","gbMeSbzTBaBBhe4ai","cT99FNMzfjiojuNxi","nfmuKNb8zNva9Z7cd","hwFTvgNyETrhSMDmF","Qa9Lw9aqJ9SfhGRmg","5wY7T7m9FGeDMXiGz","wPmmKCDNSN5MHWgmt","QgXhCLWTtaZQGL3hE","xeu4icH3N4Drt3JSR","NPfPZr2eAbc4CvxbL"],"preMigrationTypeChildren":["QETxvfjqpsmEQmidA","ov6r9tR3sTkAafnNP","DgGsyhruH8MfmBHdx","ou6pTRDXtsWPSaKYg","fFacTzsmgaWYgik2x"]},{"key":["文章名称"],"owner":"62248bb18a6b8000163a8a5d","children":["rEEfxag92NJ4ZrCjg","DM7qxpmXCxE2vLu6b","Z2tyyQsWY7xTb2t8E","38b8JfWXSghTZRfQE","srGzxHZamEkqFMgir","ke9wh65wDcGpm7dnB","y6QDD8QEefxZKLeZj","WDgnfcktPxFNgmz5Z"],"subBlocks":["38b8JfWXSghTZRfQE","Mn7DJscqZDSbFPE2n","6rueDeCed5GTZ6pYT","ke9wh65wDcGpm7dnB","srGzxHZamEkqFMgir","ahARS96qPpJuJc6Z7","PAj2DrA6F5N4byCAy","anuNi8mPtDbxBaP6Q","J7EffAntHGgTFzhWR","3gnBsBzThWTcRRcW5","iSsPRtThrE9y4eTRB","FYvhbkQhXwwFvv9s2","YjMtaiNQWPe4Lg9id","95stecdCRMpr3iHmp","Z2tyyQsWY7xTb2t8E","DM7qxpmXCxE2vLu6b","rEEfxag92NJ4ZrCjg","y6QDD8QEefxZKLeZj"],"portalsIn":["3WDZR4Ly5vmSCstpN"],"createdAt":1647341234882,"u":1647436789490,"_id":"xeu4icH3N4Drt3JSR","docUpdated":1647351595590,"crt":{"o":{"s":{"_id":"WDgnfcktPxFNgmz5Z","s":"Draft","v":[{"i":"q","_id":"fk9Yp46oZBJkzkrbz"}]}}},"typeParents":["R7gQTq8r5vmqsJNeL"],"excludedTypeParents":[],"parent":null,"folderOpen":false,"n":1,"subBlocks,prev":["Mn7DJscqZDSbFPE2n","6rueDeCed5GTZ6pYT","ke9wh65wDcGpm7dnB","srGzxHZamEkqFMgir","ahARS96qPpJuJc6Z7","PAj2DrA6F5N4byCAy","anuNi8mPtDbxBaP6Q","J7EffAntHGgTFzhWR","3gnBsBzThWTcRRcW5","iSsPRtThrE9y4eTRB","FYvhbkQhXwwFvv9s2","YjMtaiNQWPe4Lg9id","95stecdCRMpr3iHmp","mwb7SPre49ME24ZRP","Z2tyyQsWY7xTb2t8E","DM7qxpmXCxE2vLu6b","rEEfxag92NJ4ZrCjg","y6QDD8QEefxZKLeZj"],"children,prev":["rEEfxag92NJ4ZrCjg","DM7qxpmXCxE2vLu6b","Z2tyyQsWY7xTb2t8E","mwb7SPre49ME24ZRP","srGzxHZamEkqFMgir","ke9wh65wDcGpm7dnB","y6QDD8QEefxZKLeZj","WDgnfcktPxFNgmz5Z"]},{"key":["文章名称"],"owner":"62248bb18a6b8000163a8a5d","children":["rEEfxag92NJ4ZrCjg","DM7qxpmXCxE2vLu6b","Z2tyyQsWY7xTb2t8E","38b8JfWXSghTZRfQE","srGzxHZamEkqFMgir","ke9wh65wDcGpm7dnB","y6QDD8QEefxZKLeZj","WDgnfcktPxFNgmz5Z"],"subBlocks":["38b8JfWXSghTZRfQE","Mn7DJscqZDSbFPE2n","6rueDeCed5GTZ6pYT","ke9wh65wDcGpm7dnB","srGzxHZamEkqFMgir","ahARS96qPpJuJc6Z7","PAj2DrA6F5N4byCAy","anuNi8mPtDbxBaP6Q","J7EffAntHGgTFzhWR","3gnBsBzThWTcRRcW5","iSsPRtThrE9y4eTRB","FYvhbkQhXwwFvv9s2","YjMtaiNQWPe4Lg9id","95stecdCRMpr3iHmp","Z2tyyQsWY7xTb2t8E","DM7qxpmXCxE2vLu6b","rEEfxag92NJ4ZrCjg","y6QDD8QEefxZKLeZj"],"portalsIn":["3WDZR4Ly5vmSCstpN"],"createdAt":1647341234882,"u":1647436789490,"_id":"xeu4icH3N4Drt3JSR","docUpdated":1647351595590,"crt":{"o":{"s":{"_id":"WDgnfcktPxFNgmz5Z","s":"Draft","v":[{"i":"q","_id":"fk9Yp46oZBJkzkrbz"}]}}},"typeParents":["R7gQTq8r5vmqsJNeL"],"excludedTypeParents":[],"parent":null,"folderOpen":false,"n":1,"subBlocks,prev":["Mn7DJscqZDSbFPE2n","6rueDeCed5GTZ6pYT","ke9wh65wDcGpm7dnB","srGzxHZamEkqFMgir","ahARS96qPpJuJc6Z7","PAj2DrA6F5N4byCAy","anuNi8mPtDbxBaP6Q","J7EffAntHGgTFzhWR","3gnBsBzThWTcRRcW5","iSsPRtThrE9y4eTRB","FYvhbkQhXwwFvv9s2","YjMtaiNQWPe4Lg9id","95stecdCRMpr3iHmp","mwb7SPre49ME24ZRP","Z2tyyQsWY7xTb2t8E","DM7qxpmXCxE2vLu6b","rEEfxag92NJ4ZrCjg","y6QDD8QEefxZKLeZj"],"children,prev":["rEEfxag92NJ4ZrCjg","DM7qxpmXCxE2vLu6b","Z2tyyQsWY7xTb2t8E","mwb7SPre49ME24ZRP","srGzxHZamEkqFMgir","ke9wh65wDcGpm7dnB","y6QDD8QEefxZKLeZj","WDgnfcktPxFNgmz5Z"]},{"key":["一级节点1"],"owner":"62248bb18a6b8000163a8a5d","children":["95stecdCRMpr3iHmp","YjMtaiNQWPe4Lg9id","FYvhbkQhXwwFvv9s2"],"subBlocks":["Mn7DJscqZDSbFPE2n","6rueDeCed5GTZ6pYT","FYvhbkQhXwwFvv9s2","YjMtaiNQWPe4Lg9id","95stecdCRMpr3iHmp"],"portalsIn":["xeu4icH3N4Drt3JSR"],"createdAt":1647341274780,"u":1647436801336,"_id":"rEEfxag92NJ4ZrCjg","parent":"xeu4icH3N4Drt3JSR","selectedInSearch":2,"searchAliases":[],"references":[],"references,prev":[{"q":"srGzxHZamEkqFMgir","f":"key"}]},{"key":["文章名称"],"owner":"62248bb18a6b8000163a8a5d","children":["rEEfxag92NJ4ZrCjg","DM7qxpmXCxE2vLu6b","Z2tyyQsWY7xTb2t8E","38b8JfWXSghTZRfQE","srGzxHZamEkqFMgir","ke9wh65wDcGpm7dnB","y6QDD8QEefxZKLeZj","WDgnfcktPxFNgmz5Z"],"subBlocks":["38b8JfWXSghTZRfQE","Mn7DJscqZDSbFPE2n","6rueDeCed5GTZ6pYT","ke9wh65wDcGpm7dnB","srGzxHZamEkqFMgir","ahARS96qPpJuJc6Z7","PAj2DrA6F5N4byCAy","anuNi8mPtDbxBaP6Q","J7EffAntHGgTFzhWR","3gnBsBzThWTcRRcW5","iSsPRtThrE9y4eTRB","FYvhbkQhXwwFvv9s2","YjMtaiNQWPe4Lg9id","95stecdCRMpr3iHmp","Z2tyyQsWY7xTb2t8E","DM7qxpmXCxE2vLu6b","rEEfxag92NJ4ZrCjg","y6QDD8QEefxZKLeZj"],"portalsIn":["3WDZR4Ly5vmSCstpN"],"createdAt":1647341234882,"u":1647436789490,"_id":"xeu4icH3N4Drt3JSR","docUpdated":1647351595590,"crt":{"o":{"s":{"_id":"WDgnfcktPxFNgmz5Z","s":"Draft","v":[{"i":"q","_id":"fk9Yp46oZBJkzkrbz"}]}}},"typeParents":["R7gQTq8r5vmqsJNeL"],"excludedTypeParents":[],"parent":null,"folderOpen":false,"n":1,"subBlocks,prev":["Mn7DJscqZDSbFPE2n","6rueDeCed5GTZ6pYT","ke9wh65wDcGpm7dnB","srGzxHZamEkqFMgir","ahARS96qPpJuJc6Z7","PAj2DrA6F5N4byCAy","anuNi8mPtDbxBaP6Q","J7EffAntHGgTFzhWR","3gnBsBzThWTcRRcW5","iSsPRtThrE9y4eTRB","FYvhbkQhXwwFvv9s2","YjMtaiNQWPe4Lg9id","95stecdCRMpr3iHmp","mwb7SPre49ME24ZRP","Z2tyyQsWY7xTb2t8E","DM7qxpmXCxE2vLu6b","rEEfxag92NJ4ZrCjg","y6QDD8QEefxZKLeZj"],"children,prev":["rEEfxag92NJ4ZrCjg","DM7qxpmXCxE2vLu6b","Z2tyyQsWY7xTb2t8E","mwb7SPre49ME24ZRP","srGzxHZamEkqFMgir","ke9wh65wDcGpm7dnB","y6QDD8QEefxZKLeZj","WDgnfcktPxFNgmz5Z"]},{"key":["一级节点1"],"owner":"62248bb18a6b8000163a8a5d","children":["95stecdCRMpr3iHmp","YjMtaiNQWPe4Lg9id","FYvhbkQhXwwFvv9s2"],"subBlocks":["Mn7DJscqZDSbFPE2n","6rueDeCed5GTZ6pYT","FYvhbkQhXwwFvv9s2","YjMtaiNQWPe4Lg9id","95stecdCRMpr3iHmp"],"portalsIn":["xeu4icH3N4Drt3JSR"],"createdAt":1647341274780,"u":1647436801336,"_id":"rEEfxag92NJ4ZrCjg","parent":"xeu4icH3N4Drt3JSR","selectedInSearch":2,"searchAliases":[],"references":[],"references,prev":[{"q":"srGzxHZamEkqFMgir","f":"key"}]},{"key":["二级节点1.1"],"owner":"62248bb18a6b8000163a8a5d","children":["6rueDeCed5GTZ6pYT","Mn7DJscqZDSbFPE2n"],"subBlocks":["Mn7DJscqZDSbFPE2n","6rueDeCed5GTZ6pYT"],"portalsIn":["rEEfxag92NJ4ZrCjg","xeu4icH3N4Drt3JSR"],"createdAt":1647341332601,"u":1647426890619,"_id":"95stecdCRMpr3iHmp","parent":"rEEfxag92NJ4ZrCjg","docUpdated":1647341346907},{"key":["文章名称"],"owner":"62248bb18a6b8000163a8a5d","children":["rEEfxag92NJ4ZrCjg","DM7qxpmXCxE2vLu6b","Z2tyyQsWY7xTb2t8E","38b8JfWXSghTZRfQE","srGzxHZamEkqFMgir","ke9wh65wDcGpm7dnB","y6QDD8QEefxZKLeZj","WDgnfcktPxFNgmz5Z"],"subBlocks":["38b8JfWXSghTZRfQE","Mn7DJscqZDSbFPE2n","6rueDeCed5GTZ6pYT","ke9wh65wDcGpm7dnB","srGzxHZamEkqFMgir","ahARS96qPpJuJc6Z7","PAj2DrA6F5N4byCAy","anuNi8mPtDbxBaP6Q","J7EffAntHGgTFzhWR","3gnBsBzThWTcRRcW5","iSsPRtThrE9y4eTRB","FYvhbkQhXwwFvv9s2","YjMtaiNQWPe4Lg9id","95stecdCRMpr3iHmp","Z2tyyQsWY7xTb2t8E","DM7qxpmXCxE2vLu6b","rEEfxag92NJ4ZrCjg","y6QDD8QEefxZKLeZj"],"portalsIn":["3WDZR4Ly5vmSCstpN"],"createdAt":1647341234882,"u":1647436789490,"_id":"xeu4icH3N4Drt3JSR","docUpdated":1647351595590,"crt":{"o":{"s":{"_id":"WDgnfcktPxFNgmz5Z","s":"Draft","v":[{"i":"q","_id":"fk9Yp46oZBJkzkrbz"}]}}},"typeParents":["R7gQTq8r5vmqsJNeL"],"excludedTypeParents":[],"parent":null,"folderOpen":false,"n":1,"subBlocks,prev":["Mn7DJscqZDSbFPE2n","6rueDeCed5GTZ6pYT","ke9wh65wDcGpm7dnB","srGzxHZamEkqFMgir","ahARS96qPpJuJc6Z7","PAj2DrA6F5N4byCAy","anuNi8mPtDbxBaP6Q","J7EffAntHGgTFzhWR","3gnBsBzThWTcRRcW5","iSsPRtThrE9y4eTRB","FYvhbkQhXwwFvv9s2","YjMtaiNQWPe4Lg9id","95stecdCRMpr3iHmp","mwb7SPre49ME24ZRP","Z2tyyQsWY7xTb2t8E","DM7qxpmXCxE2vLu6b","rEEfxag92NJ4ZrCjg","y6QDD8QEefxZKLeZj"],"children,prev":["rEEfxag92NJ4ZrCjg","DM7qxpmXCxE2vLu6b","Z2tyyQsWY7xTb2t8E","mwb7SPre49ME24ZRP","srGzxHZamEkqFMgir","ke9wh65wDcGpm7dnB","y6QDD8QEefxZKLeZj","WDgnfcktPxFNgmz5Z"]},{"key":["一级节点1"],"owner":"62248bb18a6b8000163a8a5d","children":["95stecdCRMpr3iHmp","YjMtaiNQWPe4Lg9id","FYvhbkQhXwwFvv9s2"],"subBlocks":["Mn7DJscqZDSbFPE2n","6rueDeCed5GTZ6pYT","FYvhbkQhXwwFvv9s2","YjMtaiNQWPe4Lg9id","95stecdCRMpr3iHmp"],"portalsIn":["xeu4icH3N4Drt3JSR"],"createdAt":1647341274780,"u":1647436801336,"_id":"rEEfxag92NJ4ZrCjg","parent":"xeu4icH3N4Drt3JSR","selectedInSearch":2,"searchAliases":[],"references":[],"references,prev":[{"q":"srGzxHZamEkqFMgir","f":"key"}]},{"key":["二级节点1.1"],"owner":"62248bb18a6b8000163a8a5d","children":["6rueDeCed5GTZ6pYT","Mn7DJscqZDSbFPE2n"],"subBlocks":["Mn7DJscqZDSbFPE2n","6rueDeCed5GTZ6pYT"],"portalsIn":["rEEfxag92NJ4ZrCjg","xeu4icH3N4Drt3JSR"],"createdAt":1647341332601,"u":1647426890619,"_id":"95stecdCRMpr3iHmp","parent":"rEEfxag92NJ4ZrCjg","docUpdated":1647341346907},{"key":["三级节点1.1.1"],"owner":"62248bb18a6b8000163a8a5d","children":[],"subBlocks":[],"portalsIn":["xeu4icH3N4Drt3JSR","95stecdCRMpr3iHmp","rEEfxag92NJ4ZrCjg"],"createdAt":1647426881289,"u":1647426890667,"_id":"6rueDeCed5GTZ6pYT","parent":"95stecdCRMpr3iHmp"},{"key":["文章名称"],"owner":"62248bb18a6b8000163a8a5d","children":["rEEfxag92NJ4ZrCjg","DM7qxpmXCxE2vLu6b","Z2tyyQsWY7xTb2t8E","38b8JfWXSghTZRfQE","srGzxHZamEkqFMgir","ke9wh65wDcGpm7dnB","y6QDD8QEefxZKLeZj","WDgnfcktPxFNgmz5Z"],"subBlocks":["38b8JfWXSghTZRfQE","Mn7DJscqZDSbFPE2n","6rueDeCed5GTZ6pYT","ke9wh65wDcGpm7dnB","srGzxHZamEkqFMgir","ahARS96qPpJuJc6Z7","PAj2DrA6F5N4byCAy","anuNi8mPtDbxBaP6Q","J7EffAntHGgTFzhWR","3gnBsBzThWTcRRcW5","iSsPRtThrE9y4eTRB","FYvhbkQhXwwFvv9s2","YjMtaiNQWPe4Lg9id","95stecdCRMpr3iHmp","Z2tyyQsWY7xTb2t8E","DM7qxpmXCxE2vLu6b","rEEfxag92NJ4ZrCjg","y6QDD8QEefxZKLeZj"],"portalsIn":["3WDZR4Ly5vmSCstpN"],"createdAt":1647341234882,"u":1647436789490,"_id":"xeu4icH3N4Drt3JSR","docUpdated":1647351595590,"crt":{"o":{"s":{"_id":"WDgnfcktPxFNgmz5Z","s":"Draft","v":[{"i":"q","_id":"fk9Yp46oZBJkzkrbz"}]}}},"typeParents":["R7gQTq8r5vmqsJNeL"],"excludedTypeParents":[],"parent":null,"folderOpen":false,"n":1,"subBlocks,prev":["Mn7DJscqZDSbFPE2n","6rueDeCed5GTZ6pYT","ke9wh65wDcGpm7dnB","srGzxHZamEkqFMgir","ahARS96qPpJuJc6Z7","PAj2DrA6F5N4byCAy","anuNi8mPtDbxBaP6Q","J7EffAntHGgTFzhWR","3gnBsBzThWTcRRcW5","iSsPRtThrE9y4eTRB","FYvhbkQhXwwFvv9s2","YjMtaiNQWPe4Lg9id","95stecdCRMpr3iHmp","mwb7SPre49ME24ZRP","Z2tyyQsWY7xTb2t8E","DM7qxpmXCxE2vLu6b","rEEfxag92NJ4ZrCjg","y6QDD8QEefxZKLeZj"],"children,prev":["rEEfxag92NJ4ZrCjg","DM7qxpmXCxE2vLu6b","Z2tyyQsWY7xTb2t8E","mwb7SPre49ME24ZRP","srGzxHZamEkqFMgir","ke9wh65wDcGpm7dnB","y6QDD8QEefxZKLeZj","WDgnfcktPxFNgmz5Z"]},{"key":["一级节点1"],"owner":"62248bb18a6b8000163a8a5d","children":["95stecdCRMpr3iHmp","YjMtaiNQWPe4Lg9id","FYvhbkQhXwwFvv9s2"],"subBlocks":["Mn7DJscqZDSbFPE2n","6rueDeCed5GTZ6pYT","FYvhbkQhXwwFvv9s2","YjMtaiNQWPe4Lg9id","95stecdCRMpr3iHmp"],"portalsIn":["xeu4icH3N4Drt3JSR"],"createdAt":1647341274780,"u":1647436801336,"_id":"rEEfxag92NJ4ZrCjg","parent":"xeu4icH3N4Drt3JSR","selectedInSearch":2,"searchAliases":[],"references":[],"references,prev":[{"q":"srGzxHZamEkqFMgir","f":"key"}]},{"key":["二级节点1.1"],"owner":"62248bb18a6b8000163a8a5d","children":["6rueDeCed5GTZ6pYT","Mn7DJscqZDSbFPE2n"],"subBlocks":["Mn7DJscqZDSbFPE2n","6rueDeCed5GTZ6pYT"],"portalsIn":["rEEfxag92NJ4ZrCjg","xeu4icH3N4Drt3JSR"],"createdAt":1647341332601,"u":1647426890619,"_id":"95stecdCRMpr3iHmp","parent":"rEEfxag92NJ4ZrCjg","docUpdated":1647341346907},{"key":["三级节点1.1.2 "],"owner":"62248bb18a6b8000163a8a5d","children":[],"subBlocks":[],"portalsIn":["95stecdCRMpr3iHmp","rEEfxag92NJ4ZrCjg","xeu4icH3N4Drt3JSR"],"createdAt":1647426890618,"u":1647426902176,"_id":"Mn7DJscqZDSbFPE2n","parent":"95stecdCRMpr3iHmp"},{"key":["文章名称"],"owner":"62248bb18a6b8000163a8a5d","children":["rEEfxag92NJ4ZrCjg","DM7qxpmXCxE2vLu6b","Z2tyyQsWY7xTb2t8E","38b8JfWXSghTZRfQE","srGzxHZamEkqFMgir","ke9wh65wDcGpm7dnB","y6QDD8QEefxZKLeZj","WDgnfcktPxFNgmz5Z"],"subBlocks":["38b8JfWXSghTZRfQE","Mn7DJscqZDSbFPE2n","6rueDeCed5GTZ6pYT","ke9wh65wDcGpm7dnB","srGzxHZamEkqFMgir","ahARS96qPpJuJc6Z7","PAj2DrA6F5N4byCAy","anuNi8mPtDbxBaP6Q","J7EffAntHGgTFzhWR","3gnBsBzThWTcRRcW5","iSsPRtThrE9y4eTRB","FYvhbkQhXwwFvv9s2","YjMtaiNQWPe4Lg9id","95stecdCRMpr3iHmp","Z2tyyQsWY7xTb2t8E","DM7qxpmXCxE2vLu6b","rEEfxag92NJ4ZrCjg","y6QDD8QEefxZKLeZj"],"portalsIn":["3WDZR4Ly5vmSCstpN"],"createdAt":1647341234882,"u":1647436789490,"_id":"xeu4icH3N4Drt3JSR","docUpdated":1647351595590,"crt":{"o":{"s":{"_id":"WDgnfcktPxFNgmz5Z","s":"Draft","v":[{"i":"q","_id":"fk9Yp46oZBJkzkrbz"}]}}},"typeParents":["R7gQTq8r5vmqsJNeL"],"excludedTypeParents":[],"parent":null,"folderOpen":false,"n":1,"subBlocks,prev":["Mn7DJscqZDSbFPE2n","6rueDeCed5GTZ6pYT","ke9wh65wDcGpm7dnB","srGzxHZamEkqFMgir","ahARS96qPpJuJc6Z7","PAj2DrA6F5N4byCAy","anuNi8mPtDbxBaP6Q","J7EffAntHGgTFzhWR","3gnBsBzThWTcRRcW5","iSsPRtThrE9y4eTRB","FYvhbkQhXwwFvv9s2","YjMtaiNQWPe4Lg9id","95stecdCRMpr3iHmp","mwb7SPre49ME24ZRP","Z2tyyQsWY7xTb2t8E","DM7qxpmXCxE2vLu6b","rEEfxag92NJ4ZrCjg","y6QDD8QEefxZKLeZj"],"children,prev":["rEEfxag92NJ4ZrCjg","DM7qxpmXCxE2vLu6b","Z2tyyQsWY7xTb2t8E","mwb7SPre49ME24ZRP","srGzxHZamEkqFMgir","ke9wh65wDcGpm7dnB","y6QDD8QEefxZKLeZj","WDgnfcktPxFNgmz5Z"]},{"key":["一级节点1"],"owner":"62248bb18a6b8000163a8a5d","children":["95stecdCRMpr3iHmp","YjMtaiNQWPe4Lg9id","FYvhbkQhXwwFvv9s2"],"subBlocks":["Mn7DJscqZDSbFPE2n","6rueDeCed5GTZ6pYT","FYvhbkQhXwwFvv9s2","YjMtaiNQWPe4Lg9id","95stecdCRMpr3iHmp"],"portalsIn":["xeu4icH3N4Drt3JSR"],"createdAt":1647341274780,"u":1647436801336,"_id":"rEEfxag92NJ4ZrCjg","parent":"xeu4icH3N4Drt3JSR","selectedInSearch":2,"searchAliases":[],"references":[],"references,prev":[{"q":"srGzxHZamEkqFMgir","f":"key"}]},{"key":["二级节点1.2"],"owner":"62248bb18a6b8000163a8a5d","children":[],"subBlocks":[],"portalsIn":["rEEfxag92NJ4ZrCjg","xeu4icH3N4Drt3JSR"],"createdAt":1647341352220,"u":1647341362796,"_id":"YjMtaiNQWPe4Lg9id","parent":"rEEfxag92NJ4ZrCjg"},{"key":["文章名称"],"owner":"62248bb18a6b8000163a8a5d","children":["rEEfxag92NJ4ZrCjg","DM7qxpmXCxE2vLu6b","Z2tyyQsWY7xTb2t8E","38b8JfWXSghTZRfQE","srGzxHZamEkqFMgir","ke9wh65wDcGpm7dnB","y6QDD8QEefxZKLeZj","WDgnfcktPxFNgmz5Z"],"subBlocks":["38b8JfWXSghTZRfQE","Mn7DJscqZDSbFPE2n","6rueDeCed5GTZ6pYT","ke9wh65wDcGpm7dnB","srGzxHZamEkqFMgir","ahARS96qPpJuJc6Z7","PAj2DrA6F5N4byCAy","anuNi8mPtDbxBaP6Q","J7EffAntHGgTFzhWR","3gnBsBzThWTcRRcW5","iSsPRtThrE9y4eTRB","FYvhbkQhXwwFvv9s2","YjMtaiNQWPe4Lg9id","95stecdCRMpr3iHmp","Z2tyyQsWY7xTb2t8E","DM7qxpmXCxE2vLu6b","rEEfxag92NJ4ZrCjg","y6QDD8QEefxZKLeZj"],"portalsIn":["3WDZR4Ly5vmSCstpN"],"createdAt":1647341234882,"u":1647436789490,"_id":"xeu4icH3N4Drt3JSR","docUpdated":1647351595590,"crt":{"o":{"s":{"_id":"WDgnfcktPxFNgmz5Z","s":"Draft","v":[{"i":"q","_id":"fk9Yp46oZBJkzkrbz"}]}}},"typeParents":["R7gQTq8r5vmqsJNeL"],"excludedTypeParents":[],"parent":null,"folderOpen":false,"n":1,"subBlocks,prev":["Mn7DJscqZDSbFPE2n","6rueDeCed5GTZ6pYT","ke9wh65wDcGpm7dnB","srGzxHZamEkqFMgir","ahARS96qPpJuJc6Z7","PAj2DrA6F5N4byCAy","anuNi8mPtDbxBaP6Q","J7EffAntHGgTFzhWR","3gnBsBzThWTcRRcW5","iSsPRtThrE9y4eTRB","FYvhbkQhXwwFvv9s2","YjMtaiNQWPe4Lg9id","95stecdCRMpr3iHmp","mwb7SPre49ME24ZRP","Z2tyyQsWY7xTb2t8E","DM7qxpmXCxE2vLu6b","rEEfxag92NJ4ZrCjg","y6QDD8QEefxZKLeZj"],"children,prev":["rEEfxag92NJ4ZrCjg","DM7qxpmXCxE2vLu6b","Z2tyyQsWY7xTb2t8E","mwb7SPre49ME24ZRP","srGzxHZamEkqFMgir","ke9wh65wDcGpm7dnB","y6QDD8QEefxZKLeZj","WDgnfcktPxFNgmz5Z"]},{"key":["一级节点1"],"owner":"62248bb18a6b8000163a8a5d","children":["95stecdCRMpr3iHmp","YjMtaiNQWPe4Lg9id","FYvhbkQhXwwFvv9s2"],"subBlocks":["Mn7DJscqZDSbFPE2n","6rueDeCed5GTZ6pYT","FYvhbkQhXwwFvv9s2","YjMtaiNQWPe4Lg9id","95stecdCRMpr3iHmp"],"portalsIn":["xeu4icH3N4Drt3JSR"],"createdAt":1647341274780,"u":1647436801336,"_id":"rEEfxag92NJ4ZrCjg","parent":"xeu4icH3N4Drt3JSR","selectedInSearch":2,"searchAliases":[],"references":[],"references,prev":[{"q":"srGzxHZamEkqFMgir","f":"key"}]},{"key":["二级节点1.3"],"owner":"62248bb18a6b8000163a8a5d","children":[],"subBlocks":[],"portalsIn":["rEEfxag92NJ4ZrCjg","xeu4icH3N4Drt3JSR"],"createdAt":1647341362781,"u":1647341364257,"_id":"FYvhbkQhXwwFvv9s2","parent":"rEEfxag92NJ4ZrCjg"},{"key":["文章名称"],"owner":"62248bb18a6b8000163a8a5d","children":["rEEfxag92NJ4ZrCjg","DM7qxpmXCxE2vLu6b","Z2tyyQsWY7xTb2t8E","38b8JfWXSghTZRfQE","srGzxHZamEkqFMgir","ke9wh65wDcGpm7dnB","y6QDD8QEefxZKLeZj","WDgnfcktPxFNgmz5Z"],"subBlocks":["38b8JfWXSghTZRfQE","Mn7DJscqZDSbFPE2n","6rueDeCed5GTZ6pYT","ke9wh65wDcGpm7dnB","srGzxHZamEkqFMgir","ahARS96qPpJuJc6Z7","PAj2DrA6F5N4byCAy","anuNi8mPtDbxBaP6Q","J7EffAntHGgTFzhWR","3gnBsBzThWTcRRcW5","iSsPRtThrE9y4eTRB","FYvhbkQhXwwFvv9s2","YjMtaiNQWPe4Lg9id","95stecdCRMpr3iHmp","Z2tyyQsWY7xTb2t8E","DM7qxpmXCxE2vLu6b","rEEfxag92NJ4ZrCjg","y6QDD8QEefxZKLeZj"],"portalsIn":["3WDZR4Ly5vmSCstpN"],"createdAt":1647341234882,"u":1647436789490,"_id":"xeu4icH3N4Drt3JSR","docUpdated":1647351595590,"crt":{"o":{"s":{"_id":"WDgnfcktPxFNgmz5Z","s":"Draft","v":[{"i":"q","_id":"fk9Yp46oZBJkzkrbz"}]}}},"typeParents":["R7gQTq8r5vmqsJNeL"],"excludedTypeParents":[],"parent":null,"folderOpen":false,"n":1,"subBlocks,prev":["Mn7DJscqZDSbFPE2n","6rueDeCed5GTZ6pYT","ke9wh65wDcGpm7dnB","srGzxHZamEkqFMgir","ahARS96qPpJuJc6Z7","PAj2DrA6F5N4byCAy","anuNi8mPtDbxBaP6Q","J7EffAntHGgTFzhWR","3gnBsBzThWTcRRcW5","iSsPRtThrE9y4eTRB","FYvhbkQhXwwFvv9s2","YjMtaiNQWPe4Lg9id","95stecdCRMpr3iHmp","mwb7SPre49ME24ZRP","Z2tyyQsWY7xTb2t8E","DM7qxpmXCxE2vLu6b","rEEfxag92NJ4ZrCjg","y6QDD8QEefxZKLeZj"],"children,prev":["rEEfxag92NJ4ZrCjg","DM7qxpmXCxE2vLu6b","Z2tyyQsWY7xTb2t8E","mwb7SPre49ME24ZRP","srGzxHZamEkqFMgir","ke9wh65wDcGpm7dnB","y6QDD8QEefxZKLeZj","WDgnfcktPxFNgmz5Z"]},{"key":["一级节点2"],"owner":"62248bb18a6b8000163a8a5d","children":["iSsPRtThrE9y4eTRB","3gnBsBzThWTcRRcW5","J7EffAntHGgTFzhWR"],"subBlocks":["J7EffAntHGgTFzhWR","3gnBsBzThWTcRRcW5","iSsPRtThrE9y4eTRB"],"portalsIn":["xeu4icH3N4Drt3JSR"],"createdAt":1647341288164,"u":1647341370087,"_id":"DM7qxpmXCxE2vLu6b","parent":"xeu4icH3N4Drt3JSR"},{"key":["文章名称"],"owner":"62248bb18a6b8000163a8a5d","children":["rEEfxag92NJ4ZrCjg","DM7qxpmXCxE2vLu6b","Z2tyyQsWY7xTb2t8E","38b8JfWXSghTZRfQE","srGzxHZamEkqFMgir","ke9wh65wDcGpm7dnB","y6QDD8QEefxZKLeZj","WDgnfcktPxFNgmz5Z"],"subBlocks":["38b8JfWXSghTZRfQE","Mn7DJscqZDSbFPE2n","6rueDeCed5GTZ6pYT","ke9wh65wDcGpm7dnB","srGzxHZamEkqFMgir","ahARS96qPpJuJc6Z7","PAj2DrA6F5N4byCAy","anuNi8mPtDbxBaP6Q","J7EffAntHGgTFzhWR","3gnBsBzThWTcRRcW5","iSsPRtThrE9y4eTRB","FYvhbkQhXwwFvv9s2","YjMtaiNQWPe4Lg9id","95stecdCRMpr3iHmp","Z2tyyQsWY7xTb2t8E","DM7qxpmXCxE2vLu6b","rEEfxag92NJ4ZrCjg","y6QDD8QEefxZKLeZj"],"portalsIn":["3WDZR4Ly5vmSCstpN"],"createdAt":1647341234882,"u":1647436789490,"_id":"xeu4icH3N4Drt3JSR","docUpdated":1647351595590,"crt":{"o":{"s":{"_id":"WDgnfcktPxFNgmz5Z","s":"Draft","v":[{"i":"q","_id":"fk9Yp46oZBJkzkrbz"}]}}},"typeParents":["R7gQTq8r5vmqsJNeL"],"excludedTypeParents":[],"parent":null,"folderOpen":false,"n":1,"subBlocks,prev":["Mn7DJscqZDSbFPE2n","6rueDeCed5GTZ6pYT","ke9wh65wDcGpm7dnB","srGzxHZamEkqFMgir","ahARS96qPpJuJc6Z7","PAj2DrA6F5N4byCAy","anuNi8mPtDbxBaP6Q","J7EffAntHGgTFzhWR","3gnBsBzThWTcRRcW5","iSsPRtThrE9y4eTRB","FYvhbkQhXwwFvv9s2","YjMtaiNQWPe4Lg9id","95stecdCRMpr3iHmp","mwb7SPre49ME24ZRP","Z2tyyQsWY7xTb2t8E","DM7qxpmXCxE2vLu6b","rEEfxag92NJ4ZrCjg","y6QDD8QEefxZKLeZj"],"children,prev":["rEEfxag92NJ4ZrCjg","DM7qxpmXCxE2vLu6b","Z2tyyQsWY7xTb2t8E","mwb7SPre49ME24ZRP","srGzxHZamEkqFMgir","ke9wh65wDcGpm7dnB","y6QDD8QEefxZKLeZj","WDgnfcktPxFNgmz5Z"]},{"key":["一级节点2"],"owner":"62248bb18a6b8000163a8a5d","children":["iSsPRtThrE9y4eTRB","3gnBsBzThWTcRRcW5","J7EffAntHGgTFzhWR"],"subBlocks":["J7EffAntHGgTFzhWR","3gnBsBzThWTcRRcW5","iSsPRtThrE9y4eTRB"],"portalsIn":["xeu4icH3N4Drt3JSR"],"createdAt":1647341288164,"u":1647341370087,"_id":"DM7qxpmXCxE2vLu6b","parent":"xeu4icH3N4Drt3JSR"},{"key":["二级节点2.1"],"owner":"62248bb18a6b8000163a8a5d","children":[],"subBlocks":[],"portalsIn":["DM7qxpmXCxE2vLu6b","xeu4icH3N4Drt3JSR"],"createdAt":1647341365992,"u":1647341381730,"_id":"iSsPRtThrE9y4eTRB","parent":"DM7qxpmXCxE2vLu6b"},{"key":["文章名称"],"owner":"62248bb18a6b8000163a8a5d","children":["rEEfxag92NJ4ZrCjg","DM7qxpmXCxE2vLu6b","Z2tyyQsWY7xTb2t8E","38b8JfWXSghTZRfQE","srGzxHZamEkqFMgir","ke9wh65wDcGpm7dnB","y6QDD8QEefxZKLeZj","WDgnfcktPxFNgmz5Z"],"subBlocks":["38b8JfWXSghTZRfQE","Mn7DJscqZDSbFPE2n","6rueDeCed5GTZ6pYT","ke9wh65wDcGpm7dnB","srGzxHZamEkqFMgir","ahARS96qPpJuJc6Z7","PAj2DrA6F5N4byCAy","anuNi8mPtDbxBaP6Q","J7EffAntHGgTFzhWR","3gnBsBzThWTcRRcW5","iSsPRtThrE9y4eTRB","FYvhbkQhXwwFvv9s2","YjMtaiNQWPe4Lg9id","95stecdCRMpr3iHmp","Z2tyyQsWY7xTb2t8E","DM7qxpmXCxE2vLu6b","rEEfxag92NJ4ZrCjg","y6QDD8QEefxZKLeZj"],"portalsIn":["3WDZR4Ly5vmSCstpN"],"createdAt":1647341234882,"u":1647436789490,"_id":"xeu4icH3N4Drt3JSR","docUpdated":1647351595590,"crt":{"o":{"s":{"_id":"WDgnfcktPxFNgmz5Z","s":"Draft","v":[{"i":"q","_id":"fk9Yp46oZBJkzkrbz"}]}}},"typeParents":["R7gQTq8r5vmqsJNeL"],"excludedTypeParents":[],"parent":null,"folderOpen":false,"n":1,"subBlocks,prev":["Mn7DJscqZDSbFPE2n","6rueDeCed5GTZ6pYT","ke9wh65wDcGpm7dnB","srGzxHZamEkqFMgir","ahARS96qPpJuJc6Z7","PAj2DrA6F5N4byCAy","anuNi8mPtDbxBaP6Q","J7EffAntHGgTFzhWR","3gnBsBzThWTcRRcW5","iSsPRtThrE9y4eTRB","FYvhbkQhXwwFvv9s2","YjMtaiNQWPe4Lg9id","95stecdCRMpr3iHmp","mwb7SPre49ME24ZRP","Z2tyyQsWY7xTb2t8E","DM7qxpmXCxE2vLu6b","rEEfxag92NJ4ZrCjg","y6QDD8QEefxZKLeZj"],"children,prev":["rEEfxag92NJ4ZrCjg","DM7qxpmXCxE2vLu6b","Z2tyyQsWY7xTb2t8E","mwb7SPre49ME24ZRP","srGzxHZamEkqFMgir","ke9wh65wDcGpm7dnB","y6QDD8QEefxZKLeZj","WDgnfcktPxFNgmz5Z"]},{"key":["一级节点2"],"owner":"62248bb18a6b8000163a8a5d","children":["iSsPRtThrE9y4eTRB","3gnBsBzThWTcRRcW5","J7EffAntHGgTFzhWR"],"subBlocks":["J7EffAntHGgTFzhWR","3gnBsBzThWTcRRcW5","iSsPRtThrE9y4eTRB"],"portalsIn":["xeu4icH3N4Drt3JSR"],"createdAt":1647341288164,"u":1647341370087,"_id":"DM7qxpmXCxE2vLu6b","parent":"xeu4icH3N4Drt3JSR"},{"key":["二级节点2.2"],"owner":"62248bb18a6b8000163a8a5d","children":[],"subBlocks":[],"portalsIn":["DM7qxpmXCxE2vLu6b","xeu4icH3N4Drt3JSR"],"createdAt":1647341369426,"u":1647341378268,"_id":"3gnBsBzThWTcRRcW5","parent":"DM7qxpmXCxE2vLu6b"},{"key":["文章名称"],"owner":"62248bb18a6b8000163a8a5d","children":["rEEfxag92NJ4ZrCjg","DM7qxpmXCxE2vLu6b","Z2tyyQsWY7xTb2t8E","38b8JfWXSghTZRfQE","srGzxHZamEkqFMgir","ke9wh65wDcGpm7dnB","y6QDD8QEefxZKLeZj","WDgnfcktPxFNgmz5Z"],"subBlocks":["38b8JfWXSghTZRfQE","Mn7DJscqZDSbFPE2n","6rueDeCed5GTZ6pYT","ke9wh65wDcGpm7dnB","srGzxHZamEkqFMgir","ahARS96qPpJuJc6Z7","PAj2DrA6F5N4byCAy","anuNi8mPtDbxBaP6Q","J7EffAntHGgTFzhWR","3gnBsBzThWTcRRcW5","iSsPRtThrE9y4eTRB","FYvhbkQhXwwFvv9s2","YjMtaiNQWPe4Lg9id","95stecdCRMpr3iHmp","Z2tyyQsWY7xTb2t8E","DM7qxpmXCxE2vLu6b","rEEfxag92NJ4ZrCjg","y6QDD8QEefxZKLeZj"],"portalsIn":["3WDZR4Ly5vmSCstpN"],"createdAt":1647341234882,"u":1647436789490,"_id":"xeu4icH3N4Drt3JSR","docUpdated":1647351595590,"crt":{"o":{"s":{"_id":"WDgnfcktPxFNgmz5Z","s":"Draft","v":[{"i":"q","_id":"fk9Yp46oZBJkzkrbz"}]}}},"typeParents":["R7gQTq8r5vmqsJNeL"],"excludedTypeParents":[],"parent":null,"folderOpen":false,"n":1,"subBlocks,prev":["Mn7DJscqZDSbFPE2n","6rueDeCed5GTZ6pYT","ke9wh65wDcGpm7dnB","srGzxHZamEkqFMgir","ahARS96qPpJuJc6Z7","PAj2DrA6F5N4byCAy","anuNi8mPtDbxBaP6Q","J7EffAntHGgTFzhWR","3gnBsBzThWTcRRcW5","iSsPRtThrE9y4eTRB","FYvhbkQhXwwFvv9s2","YjMtaiNQWPe4Lg9id","95stecdCRMpr3iHmp","mwb7SPre49ME24ZRP","Z2tyyQsWY7xTb2t8E","DM7qxpmXCxE2vLu6b","rEEfxag92NJ4ZrCjg","y6QDD8QEefxZKLeZj"],"children,prev":["rEEfxag92NJ4ZrCjg","DM7qxpmXCxE2vLu6b","Z2tyyQsWY7xTb2t8E","mwb7SPre49ME24ZRP","srGzxHZamEkqFMgir","ke9wh65wDcGpm7dnB","y6QDD8QEefxZKLeZj","WDgnfcktPxFNgmz5Z"]},{"key":["一级节点2"],"owner":"62248bb18a6b8000163a8a5d","children":["iSsPRtThrE9y4eTRB","3gnBsBzThWTcRRcW5","J7EffAntHGgTFzhWR"],"subBlocks":["J7EffAntHGgTFzhWR","3gnBsBzThWTcRRcW5","iSsPRtThrE9y4eTRB"],"portalsIn":["xeu4icH3N4Drt3JSR"],"createdAt":1647341288164,"u":1647341370087,"_id":"DM7qxpmXCxE2vLu6b","parent":"xeu4icH3N4Drt3JSR"},{"key":["二级节点2.3"],"owner":"62248bb18a6b8000163a8a5d","children":[],"subBlocks":[],"portalsIn":["DM7qxpmXCxE2vLu6b","xeu4icH3N4Drt3JSR"],"createdAt":1647341370086,"u":1647341375389,"_id":"J7EffAntHGgTFzhWR","parent":"DM7qxpmXCxE2vLu6b"},{"key":["文章名称"],"owner":"62248bb18a6b8000163a8a5d","children":["rEEfxag92NJ4ZrCjg","DM7qxpmXCxE2vLu6b","Z2tyyQsWY7xTb2t8E","38b8JfWXSghTZRfQE","srGzxHZamEkqFMgir","ke9wh65wDcGpm7dnB","y6QDD8QEefxZKLeZj","WDgnfcktPxFNgmz5Z"],"subBlocks":["38b8JfWXSghTZRfQE","Mn7DJscqZDSbFPE2n","6rueDeCed5GTZ6pYT","ke9wh65wDcGpm7dnB","srGzxHZamEkqFMgir","ahARS96qPpJuJc6Z7","PAj2DrA6F5N4byCAy","anuNi8mPtDbxBaP6Q","J7EffAntHGgTFzhWR","3gnBsBzThWTcRRcW5","iSsPRtThrE9y4eTRB","FYvhbkQhXwwFvv9s2","YjMtaiNQWPe4Lg9id","95stecdCRMpr3iHmp","Z2tyyQsWY7xTb2t8E","DM7qxpmXCxE2vLu6b","rEEfxag92NJ4ZrCjg","y6QDD8QEefxZKLeZj"],"portalsIn":["3WDZR4Ly5vmSCstpN"],"createdAt":1647341234882,"u":1647436789490,"_id":"xeu4icH3N4Drt3JSR","docUpdated":1647351595590,"crt":{"o":{"s":{"_id":"WDgnfcktPxFNgmz5Z","s":"Draft","v":[{"i":"q","_id":"fk9Yp46oZBJkzkrbz"}]}}},"typeParents":["R7gQTq8r5vmqsJNeL"],"excludedTypeParents":[],"parent":null,"folderOpen":false,"n":1,"subBlocks,prev":["Mn7DJscqZDSbFPE2n","6rueDeCed5GTZ6pYT","ke9wh65wDcGpm7dnB","srGzxHZamEkqFMgir","ahARS96qPpJuJc6Z7","PAj2DrA6F5N4byCAy","anuNi8mPtDbxBaP6Q","J7EffAntHGgTFzhWR","3gnBsBzThWTcRRcW5","iSsPRtThrE9y4eTRB","FYvhbkQhXwwFvv9s2","YjMtaiNQWPe4Lg9id","95stecdCRMpr3iHmp","mwb7SPre49ME24ZRP","Z2tyyQsWY7xTb2t8E","DM7qxpmXCxE2vLu6b","rEEfxag92NJ4ZrCjg","y6QDD8QEefxZKLeZj"],"children,prev":["rEEfxag92NJ4ZrCjg","DM7qxpmXCxE2vLu6b","Z2tyyQsWY7xTb2t8E","mwb7SPre49ME24ZRP","srGzxHZamEkqFMgir","ke9wh65wDcGpm7dnB","y6QDD8QEefxZKLeZj","WDgnfcktPxFNgmz5Z"]},{"key":["一级节点3"],"owner":"62248bb18a6b8000163a8a5d","children":["anuNi8mPtDbxBaP6Q","PAj2DrA6F5N4byCAy","ahARS96qPpJuJc6Z7"],"subBlocks":["ahARS96qPpJuJc6Z7","PAj2DrA6F5N4byCAy","anuNi8mPtDbxBaP6Q"],"portalsIn":["xeu4icH3N4Drt3JSR"],"createdAt":1647341292745,"u":1647341391281,"_id":"Z2tyyQsWY7xTb2t8E","parent":"xeu4icH3N4Drt3JSR"},{"key":["文章名称"],"owner":"62248bb18a6b8000163a8a5d","children":["rEEfxag92NJ4ZrCjg","DM7qxpmXCxE2vLu6b","Z2tyyQsWY7xTb2t8E","38b8JfWXSghTZRfQE","srGzxHZamEkqFMgir","ke9wh65wDcGpm7dnB","y6QDD8QEefxZKLeZj","WDgnfcktPxFNgmz5Z"],"subBlocks":["38b8JfWXSghTZRfQE","Mn7DJscqZDSbFPE2n","6rueDeCed5GTZ6pYT","ke9wh65wDcGpm7dnB","srGzxHZamEkqFMgir","ahARS96qPpJuJc6Z7","PAj2DrA6F5N4byCAy","anuNi8mPtDbxBaP6Q","J7EffAntHGgTFzhWR","3gnBsBzThWTcRRcW5","iSsPRtThrE9y4eTRB","FYvhbkQhXwwFvv9s2","YjMtaiNQWPe4Lg9id","95stecdCRMpr3iHmp","Z2tyyQsWY7xTb2t8E","DM7qxpmXCxE2vLu6b","rEEfxag92NJ4ZrCjg","y6QDD8QEefxZKLeZj"],"portalsIn":["3WDZR4Ly5vmSCstpN"],"createdAt":1647341234882,"u":1647436789490,"_id":"xeu4icH3N4Drt3JSR","docUpdated":1647351595590,"crt":{"o":{"s":{"_id":"WDgnfcktPxFNgmz5Z","s":"Draft","v":[{"i":"q","_id":"fk9Yp46oZBJkzkrbz"}]}}},"typeParents":["R7gQTq8r5vmqsJNeL"],"excludedTypeParents":[],"parent":null,"folderOpen":false,"n":1,"subBlocks,prev":["Mn7DJscqZDSbFPE2n","6rueDeCed5GTZ6pYT","ke9wh65wDcGpm7dnB","srGzxHZamEkqFMgir","ahARS96qPpJuJc6Z7","PAj2DrA6F5N4byCAy","anuNi8mPtDbxBaP6Q","J7EffAntHGgTFzhWR","3gnBsBzThWTcRRcW5","iSsPRtThrE9y4eTRB","FYvhbkQhXwwFvv9s2","YjMtaiNQWPe4Lg9id","95stecdCRMpr3iHmp","mwb7SPre49ME24ZRP","Z2tyyQsWY7xTb2t8E","DM7qxpmXCxE2vLu6b","rEEfxag92NJ4ZrCjg","y6QDD8QEefxZKLeZj"],"children,prev":["rEEfxag92NJ4ZrCjg","DM7qxpmXCxE2vLu6b","Z2tyyQsWY7xTb2t8E","mwb7SPre49ME24ZRP","srGzxHZamEkqFMgir","ke9wh65wDcGpm7dnB","y6QDD8QEefxZKLeZj","WDgnfcktPxFNgmz5Z"]},{"key":["一级节点3"],"owner":"62248bb18a6b8000163a8a5d","children":["anuNi8mPtDbxBaP6Q","PAj2DrA6F5N4byCAy","ahARS96qPpJuJc6Z7"],"subBlocks":["ahARS96qPpJuJc6Z7","PAj2DrA6F5N4byCAy","anuNi8mPtDbxBaP6Q"],"portalsIn":["xeu4icH3N4Drt3JSR"],"createdAt":1647341292745,"u":1647341391281,"_id":"Z2tyyQsWY7xTb2t8E","parent":"xeu4icH3N4Drt3JSR"},{"key":["二级节点3.1"],"owner":"62248bb18a6b8000163a8a5d","children":[],"subBlocks":[],"portalsIn":["Z2tyyQsWY7xTb2t8E","xeu4icH3N4Drt3JSR"],"createdAt":1647341389436,"u":1647341396415,"_id":"anuNi8mPtDbxBaP6Q","parent":"Z2tyyQsWY7xTb2t8E"},{"key":["文章名称"],"owner":"62248bb18a6b8000163a8a5d","children":["rEEfxag92NJ4ZrCjg","DM7qxpmXCxE2vLu6b","Z2tyyQsWY7xTb2t8E","38b8JfWXSghTZRfQE","srGzxHZamEkqFMgir","ke9wh65wDcGpm7dnB","y6QDD8QEefxZKLeZj","WDgnfcktPxFNgmz5Z"],"subBlocks":["38b8JfWXSghTZRfQE","Mn7DJscqZDSbFPE2n","6rueDeCed5GTZ6pYT","ke9wh65wDcGpm7dnB","srGzxHZamEkqFMgir","ahARS96qPpJuJc6Z7","PAj2DrA6F5N4byCAy","anuNi8mPtDbxBaP6Q","J7EffAntHGgTFzhWR","3gnBsBzThWTcRRcW5","iSsPRtThrE9y4eTRB","FYvhbkQhXwwFvv9s2","YjMtaiNQWPe4Lg9id","95stecdCRMpr3iHmp","Z2tyyQsWY7xTb2t8E","DM7qxpmXCxE2vLu6b","rEEfxag92NJ4ZrCjg","y6QDD8QEefxZKLeZj"],"portalsIn":["3WDZR4Ly5vmSCstpN"],"createdAt":1647341234882,"u":1647436789490,"_id":"xeu4icH3N4Drt3JSR","docUpdated":1647351595590,"crt":{"o":{"s":{"_id":"WDgnfcktPxFNgmz5Z","s":"Draft","v":[{"i":"q","_id":"fk9Yp46oZBJkzkrbz"}]}}},"typeParents":["R7gQTq8r5vmqsJNeL"],"excludedTypeParents":[],"parent":null,"folderOpen":false,"n":1,"subBlocks,prev":["Mn7DJscqZDSbFPE2n","6rueDeCed5GTZ6pYT","ke9wh65wDcGpm7dnB","srGzxHZamEkqFMgir","ahARS96qPpJuJc6Z7","PAj2DrA6F5N4byCAy","anuNi8mPtDbxBaP6Q","J7EffAntHGgTFzhWR","3gnBsBzThWTcRRcW5","iSsPRtThrE9y4eTRB","FYvhbkQhXwwFvv9s2","YjMtaiNQWPe4Lg9id","95stecdCRMpr3iHmp","mwb7SPre49ME24ZRP","Z2tyyQsWY7xTb2t8E","DM7qxpmXCxE2vLu6b","rEEfxag92NJ4ZrCjg","y6QDD8QEefxZKLeZj"],"children,prev":["rEEfxag92NJ4ZrCjg","DM7qxpmXCxE2vLu6b","Z2tyyQsWY7xTb2t8E","mwb7SPre49ME24ZRP","srGzxHZamEkqFMgir","ke9wh65wDcGpm7dnB","y6QDD8QEefxZKLeZj","WDgnfcktPxFNgmz5Z"]},{"key":["一级节点3"],"owner":"62248bb18a6b8000163a8a5d","children":["anuNi8mPtDbxBaP6Q","PAj2DrA6F5N4byCAy","ahARS96qPpJuJc6Z7"],"subBlocks":["ahARS96qPpJuJc6Z7","PAj2DrA6F5N4byCAy","anuNi8mPtDbxBaP6Q"],"portalsIn":["xeu4icH3N4Drt3JSR"],"createdAt":1647341292745,"u":1647341391281,"_id":"Z2tyyQsWY7xTb2t8E","parent":"xeu4icH3N4Drt3JSR"},{"key":["二级节点3.2"],"owner":"62248bb18a6b8000163a8a5d","children":[],"subBlocks":[],"portalsIn":["Z2tyyQsWY7xTb2t8E","xeu4icH3N4Drt3JSR"],"createdAt":1647341390666,"u":1647341400782,"_id":"PAj2DrA6F5N4byCAy","parent":"Z2tyyQsWY7xTb2t8E"},{"key":["文章名称"],"owner":"62248bb18a6b8000163a8a5d","children":["rEEfxag92NJ4ZrCjg","DM7qxpmXCxE2vLu6b","Z2tyyQsWY7xTb2t8E","38b8JfWXSghTZRfQE","srGzxHZamEkqFMgir","ke9wh65wDcGpm7dnB","y6QDD8QEefxZKLeZj","WDgnfcktPxFNgmz5Z"],"subBlocks":["38b8JfWXSghTZRfQE","Mn7DJscqZDSbFPE2n","6rueDeCed5GTZ6pYT","ke9wh65wDcGpm7dnB","srGzxHZamEkqFMgir","ahARS96qPpJuJc6Z7","PAj2DrA6F5N4byCAy","anuNi8mPtDbxBaP6Q","J7EffAntHGgTFzhWR","3gnBsBzThWTcRRcW5","iSsPRtThrE9y4eTRB","FYvhbkQhXwwFvv9s2","YjMtaiNQWPe4Lg9id","95stecdCRMpr3iHmp","Z2tyyQsWY7xTb2t8E","DM7qxpmXCxE2vLu6b","rEEfxag92NJ4ZrCjg","y6QDD8QEefxZKLeZj"],"portalsIn":["3WDZR4Ly5vmSCstpN"],"createdAt":1647341234882,"u":1647436789490,"_id":"xeu4icH3N4Drt3JSR","docUpdated":1647351595590,"crt":{"o":{"s":{"_id":"WDgnfcktPxFNgmz5Z","s":"Draft","v":[{"i":"q","_id":"fk9Yp46oZBJkzkrbz"}]}}},"typeParents":["R7gQTq8r5vmqsJNeL"],"excludedTypeParents":[],"parent":null,"folderOpen":false,"n":1,"subBlocks,prev":["Mn7DJscqZDSbFPE2n","6rueDeCed5GTZ6pYT","ke9wh65wDcGpm7dnB","srGzxHZamEkqFMgir","ahARS96qPpJuJc6Z7","PAj2DrA6F5N4byCAy","anuNi8mPtDbxBaP6Q","J7EffAntHGgTFzhWR","3gnBsBzThWTcRRcW5","iSsPRtThrE9y4eTRB","FYvhbkQhXwwFvv9s2","YjMtaiNQWPe4Lg9id","95stecdCRMpr3iHmp","mwb7SPre49ME24ZRP","Z2tyyQsWY7xTb2t8E","DM7qxpmXCxE2vLu6b","rEEfxag92NJ4ZrCjg","y6QDD8QEefxZKLeZj"],"children,prev":["rEEfxag92NJ4ZrCjg","DM7qxpmXCxE2vLu6b","Z2tyyQsWY7xTb2t8E","mwb7SPre49ME24ZRP","srGzxHZamEkqFMgir","ke9wh65wDcGpm7dnB","y6QDD8QEefxZKLeZj","WDgnfcktPxFNgmz5Z"]},{"key":["一级节点3"],"owner":"62248bb18a6b8000163a8a5d","children":["anuNi8mPtDbxBaP6Q","PAj2DrA6F5N4byCAy","ahARS96qPpJuJc6Z7"],"subBlocks":["ahARS96qPpJuJc6Z7","PAj2DrA6F5N4byCAy","anuNi8mPtDbxBaP6Q"],"portalsIn":["xeu4icH3N4Drt3JSR"],"createdAt":1647341292745,"u":1647341391281,"_id":"Z2tyyQsWY7xTb2t8E","parent":"xeu4icH3N4Drt3JSR"},{"key":["二级节点3.3"],"owner":"62248bb18a6b8000163a8a5d","children":[],"subBlocks":[],"portalsIn":["Z2tyyQsWY7xTb2t8E","xeu4icH3N4Drt3JSR"],"createdAt":1647341391281,"u":1647341399661,"_id":"ahARS96qPpJuJc6Z7","parent":"Z2tyyQsWY7xTb2t8E"},{"key":["文章名称"],"owner":"62248bb18a6b8000163a8a5d","children":["rEEfxag92NJ4ZrCjg","DM7qxpmXCxE2vLu6b","Z2tyyQsWY7xTb2t8E","38b8JfWXSghTZRfQE","srGzxHZamEkqFMgir","ke9wh65wDcGpm7dnB","y6QDD8QEefxZKLeZj","WDgnfcktPxFNgmz5Z"],"subBlocks":["38b8JfWXSghTZRfQE","Mn7DJscqZDSbFPE2n","6rueDeCed5GTZ6pYT","ke9wh65wDcGpm7dnB","srGzxHZamEkqFMgir","ahARS96qPpJuJc6Z7","PAj2DrA6F5N4byCAy","anuNi8mPtDbxBaP6Q","J7EffAntHGgTFzhWR","3gnBsBzThWTcRRcW5","iSsPRtThrE9y4eTRB","FYvhbkQhXwwFvv9s2","YjMtaiNQWPe4Lg9id","95stecdCRMpr3iHmp","Z2tyyQsWY7xTb2t8E","DM7qxpmXCxE2vLu6b","rEEfxag92NJ4ZrCjg","y6QDD8QEefxZKLeZj"],"portalsIn":["3WDZR4Ly5vmSCstpN"],"createdAt":1647341234882,"u":1647436789490,"_id":"xeu4icH3N4Drt3JSR","docUpdated":1647351595590,"crt":{"o":{"s":{"_id":"WDgnfcktPxFNgmz5Z","s":"Draft","v":[{"i":"q","_id":"fk9Yp46oZBJkzkrbz"}]}}},"typeParents":["R7gQTq8r5vmqsJNeL"],"excludedTypeParents":[],"parent":null,"folderOpen":false,"n":1,"subBlocks,prev":["Mn7DJscqZDSbFPE2n","6rueDeCed5GTZ6pYT","ke9wh65wDcGpm7dnB","srGzxHZamEkqFMgir","ahARS96qPpJuJc6Z7","PAj2DrA6F5N4byCAy","anuNi8mPtDbxBaP6Q","J7EffAntHGgTFzhWR","3gnBsBzThWTcRRcW5","iSsPRtThrE9y4eTRB","FYvhbkQhXwwFvv9s2","YjMtaiNQWPe4Lg9id","95stecdCRMpr3iHmp","mwb7SPre49ME24ZRP","Z2tyyQsWY7xTb2t8E","DM7qxpmXCxE2vLu6b","rEEfxag92NJ4ZrCjg","y6QDD8QEefxZKLeZj"],"children,prev":["rEEfxag92NJ4ZrCjg","DM7qxpmXCxE2vLu6b","Z2tyyQsWY7xTb2t8E","mwb7SPre49ME24ZRP","srGzxHZamEkqFMgir","ke9wh65wDcGpm7dnB","y6QDD8QEefxZKLeZj","WDgnfcktPxFNgmz5Z"]},{"key":["一级节点 "],"owner":"62248bb18a6b8000163a8a5d","children":[],"subBlocks":[],"portalsIn":["xeu4icH3N4Drt3JSR"],"createdAt":1647436788129,"u":1647436793576,"_id":"38b8JfWXSghTZRfQE","parent":"xeu4icH3N4Drt3JSR","portalsIn,prev":[]},{"key":["文章名称"],"owner":"62248bb18a6b8000163a8a5d","children":["rEEfxag92NJ4ZrCjg","DM7qxpmXCxE2vLu6b","Z2tyyQsWY7xTb2t8E","38b8JfWXSghTZRfQE","srGzxHZamEkqFMgir","ke9wh65wDcGpm7dnB","y6QDD8QEefxZKLeZj","WDgnfcktPxFNgmz5Z"],"subBlocks":["38b8JfWXSghTZRfQE","Mn7DJscqZDSbFPE2n","6rueDeCed5GTZ6pYT","ke9wh65wDcGpm7dnB","srGzxHZamEkqFMgir","ahARS96qPpJuJc6Z7","PAj2DrA6F5N4byCAy","anuNi8mPtDbxBaP6Q","J7EffAntHGgTFzhWR","3gnBsBzThWTcRRcW5","iSsPRtThrE9y4eTRB","FYvhbkQhXwwFvv9s2","YjMtaiNQWPe4Lg9id","95stecdCRMpr3iHmp","Z2tyyQsWY7xTb2t8E","DM7qxpmXCxE2vLu6b","rEEfxag92NJ4ZrCjg","y6QDD8QEefxZKLeZj"],"portalsIn":["3WDZR4Ly5vmSCstpN"],"createdAt":1647341234882,"u":1647436789490,"_id":"xeu4icH3N4Drt3JSR","docUpdated":1647351595590,"crt":{"o":{"s":{"_id":"WDgnfcktPxFNgmz5Z","s":"Draft","v":[{"i":"q","_id":"fk9Yp46oZBJkzkrbz"}]}}},"typeParents":["R7gQTq8r5vmqsJNeL"],"excludedTypeParents":[],"parent":null,"folderOpen":false,"n":1,"subBlocks,prev":["Mn7DJscqZDSbFPE2n","6rueDeCed5GTZ6pYT","ke9wh65wDcGpm7dnB","srGzxHZamEkqFMgir","ahARS96qPpJuJc6Z7","PAj2DrA6F5N4byCAy","anuNi8mPtDbxBaP6Q","J7EffAntHGgTFzhWR","3gnBsBzThWTcRRcW5","iSsPRtThrE9y4eTRB","FYvhbkQhXwwFvv9s2","YjMtaiNQWPe4Lg9id","95stecdCRMpr3iHmp","mwb7SPre49ME24ZRP","Z2tyyQsWY7xTb2t8E","DM7qxpmXCxE2vLu6b","rEEfxag92NJ4ZrCjg","y6QDD8QEefxZKLeZj"],"children,prev":["rEEfxag92NJ4ZrCjg","DM7qxpmXCxE2vLu6b","Z2tyyQsWY7xTb2t8E","mwb7SPre49ME24ZRP","srGzxHZamEkqFMgir","ke9wh65wDcGpm7dnB","y6QDD8QEefxZKLeZj","WDgnfcktPxFNgmz5Z"]},{"key":["一级节点5"],"owner":"62248bb18a6b8000163a8a5d","children":[],"subBlocks":[],"portalsIn":["xeu4icH3N4Drt3JSR"],"createdAt":1647341448627,"u":1647436801327,"_id":"srGzxHZamEkqFMgir","parent":"xeu4icH3N4Drt3JSR"},{"key":["文章名称"],"owner":"62248bb18a6b8000163a8a5d","children":["rEEfxag92NJ4ZrCjg","DM7qxpmXCxE2vLu6b","Z2tyyQsWY7xTb2t8E","38b8JfWXSghTZRfQE","srGzxHZamEkqFMgir","ke9wh65wDcGpm7dnB","y6QDD8QEefxZKLeZj","WDgnfcktPxFNgmz5Z"],"subBlocks":["38b8JfWXSghTZRfQE","Mn7DJscqZDSbFPE2n","6rueDeCed5GTZ6pYT","ke9wh65wDcGpm7dnB","srGzxHZamEkqFMgir","ahARS96qPpJuJc6Z7","PAj2DrA6F5N4byCAy","anuNi8mPtDbxBaP6Q","J7EffAntHGgTFzhWR","3gnBsBzThWTcRRcW5","iSsPRtThrE9y4eTRB","FYvhbkQhXwwFvv9s2","YjMtaiNQWPe4Lg9id","95stecdCRMpr3iHmp","Z2tyyQsWY7xTb2t8E","DM7qxpmXCxE2vLu6b","rEEfxag92NJ4ZrCjg","y6QDD8QEefxZKLeZj"],"portalsIn":["3WDZR4Ly5vmSCstpN"],"createdAt":1647341234882,"u":1647436789490,"_id":"xeu4icH3N4Drt3JSR","docUpdated":1647351595590,"crt":{"o":{"s":{"_id":"WDgnfcktPxFNgmz5Z","s":"Draft","v":[{"i":"q","_id":"fk9Yp46oZBJkzkrbz"}]}}},"typeParents":["R7gQTq8r5vmqsJNeL"],"excludedTypeParents":[],"parent":null,"folderOpen":false,"n":1,"subBlocks,prev":["Mn7DJscqZDSbFPE2n","6rueDeCed5GTZ6pYT","ke9wh65wDcGpm7dnB","srGzxHZamEkqFMgir","ahARS96qPpJuJc6Z7","PAj2DrA6F5N4byCAy","anuNi8mPtDbxBaP6Q","J7EffAntHGgTFzhWR","3gnBsBzThWTcRRcW5","iSsPRtThrE9y4eTRB","FYvhbkQhXwwFvv9s2","YjMtaiNQWPe4Lg9id","95stecdCRMpr3iHmp","mwb7SPre49ME24ZRP","Z2tyyQsWY7xTb2t8E","DM7qxpmXCxE2vLu6b","rEEfxag92NJ4ZrCjg","y6QDD8QEefxZKLeZj"],"children,prev":["rEEfxag92NJ4ZrCjg","DM7qxpmXCxE2vLu6b","Z2tyyQsWY7xTb2t8E","mwb7SPre49ME24ZRP","srGzxHZamEkqFMgir","ke9wh65wDcGpm7dnB","y6QDD8QEefxZKLeZj","WDgnfcktPxFNgmz5Z"]},{"key":["一级节点6"],"owner":"62248bb18a6b8000163a8a5d","children":[],"subBlocks":[],"portalsIn":["xeu4icH3N4Drt3JSR"],"createdAt":1647341580067,"u":1647436805742,"_id":"ke9wh65wDcGpm7dnB","parent":"xeu4icH3N4Drt3JSR"},{"key":["文章名称"],"owner":"62248bb18a6b8000163a8a5d","children":["rEEfxag92NJ4ZrCjg","DM7qxpmXCxE2vLu6b","Z2tyyQsWY7xTb2t8E","38b8JfWXSghTZRfQE","srGzxHZamEkqFMgir","ke9wh65wDcGpm7dnB","y6QDD8QEefxZKLeZj","WDgnfcktPxFNgmz5Z"],"subBlocks":["38b8JfWXSghTZRfQE","Mn7DJscqZDSbFPE2n","6rueDeCed5GTZ6pYT","ke9wh65wDcGpm7dnB","srGzxHZamEkqFMgir","ahARS96qPpJuJc6Z7","PAj2DrA6F5N4byCAy","anuNi8mPtDbxBaP6Q","J7EffAntHGgTFzhWR","3gnBsBzThWTcRRcW5","iSsPRtThrE9y4eTRB","FYvhbkQhXwwFvv9s2","YjMtaiNQWPe4Lg9id","95stecdCRMpr3iHmp","Z2tyyQsWY7xTb2t8E","DM7qxpmXCxE2vLu6b","rEEfxag92NJ4ZrCjg","y6QDD8QEefxZKLeZj"],"portalsIn":["3WDZR4Ly5vmSCstpN"],"createdAt":1647341234882,"u":1647436789490,"_id":"xeu4icH3N4Drt3JSR","docUpdated":1647351595590,"crt":{"o":{"s":{"_id":"WDgnfcktPxFNgmz5Z","s":"Draft","v":[{"i":"q","_id":"fk9Yp46oZBJkzkrbz"}]}}},"typeParents":["R7gQTq8r5vmqsJNeL"],"excludedTypeParents":[],"parent":null,"folderOpen":false,"n":1,"subBlocks,prev":["Mn7DJscqZDSbFPE2n","6rueDeCed5GTZ6pYT","ke9wh65wDcGpm7dnB","srGzxHZamEkqFMgir","ahARS96qPpJuJc6Z7","PAj2DrA6F5N4byCAy","anuNi8mPtDbxBaP6Q","J7EffAntHGgTFzhWR","3gnBsBzThWTcRRcW5","iSsPRtThrE9y4eTRB","FYvhbkQhXwwFvv9s2","YjMtaiNQWPe4Lg9id","95stecdCRMpr3iHmp","mwb7SPre49ME24ZRP","Z2tyyQsWY7xTb2t8E","DM7qxpmXCxE2vLu6b","rEEfxag92NJ4ZrCjg","y6QDD8QEefxZKLeZj"],"children,prev":["rEEfxag92NJ4ZrCjg","DM7qxpmXCxE2vLu6b","Z2tyyQsWY7xTb2t8E","mwb7SPre49ME24ZRP","srGzxHZamEkqFMgir","ke9wh65wDcGpm7dnB","y6QDD8QEefxZKLeZj","WDgnfcktPxFNgmz5Z"]},{"key":[],"owner":"62248bb18a6b8000163a8a5d","children":[],"subBlocks":[],"portalsIn":["xeu4icH3N4Drt3JSR"],"createdAt":1647341250845,"u":1647341250845,"_id":"y6QDD8QEefxZKLeZj","parent":"xeu4icH3N4Drt3JSR"},{"key":["文章名称"],"owner":"62248bb18a6b8000163a8a5d","children":["rEEfxag92NJ4ZrCjg","DM7qxpmXCxE2vLu6b","Z2tyyQsWY7xTb2t8E","38b8JfWXSghTZRfQE","srGzxHZamEkqFMgir","ke9wh65wDcGpm7dnB","y6QDD8QEefxZKLeZj","WDgnfcktPxFNgmz5Z"],"subBlocks":["38b8JfWXSghTZRfQE","Mn7DJscqZDSbFPE2n","6rueDeCed5GTZ6pYT","ke9wh65wDcGpm7dnB","srGzxHZamEkqFMgir","ahARS96qPpJuJc6Z7","PAj2DrA6F5N4byCAy","anuNi8mPtDbxBaP6Q","J7EffAntHGgTFzhWR","3gnBsBzThWTcRRcW5","iSsPRtThrE9y4eTRB","FYvhbkQhXwwFvv9s2","YjMtaiNQWPe4Lg9id","95stecdCRMpr3iHmp","Z2tyyQsWY7xTb2t8E","DM7qxpmXCxE2vLu6b","rEEfxag92NJ4ZrCjg","y6QDD8QEefxZKLeZj"],"portalsIn":["3WDZR4Ly5vmSCstpN"],"createdAt":1647341234882,"u":1647436789490,"_id":"xeu4icH3N4Drt3JSR","docUpdated":1647351595590,"crt":{"o":{"s":{"_id":"WDgnfcktPxFNgmz5Z","s":"Draft","v":[{"i":"q","_id":"fk9Yp46oZBJkzkrbz"}]}}},"typeParents":["R7gQTq8r5vmqsJNeL"],"excludedTypeParents":[],"parent":null,"folderOpen":false,"n":1,"subBlocks,prev":["Mn7DJscqZDSbFPE2n","6rueDeCed5GTZ6pYT","ke9wh65wDcGpm7dnB","srGzxHZamEkqFMgir","ahARS96qPpJuJc6Z7","PAj2DrA6F5N4byCAy","anuNi8mPtDbxBaP6Q","J7EffAntHGgTFzhWR","3gnBsBzThWTcRRcW5","iSsPRtThrE9y4eTRB","FYvhbkQhXwwFvv9s2","YjMtaiNQWPe4Lg9id","95stecdCRMpr3iHmp","mwb7SPre49ME24ZRP","Z2tyyQsWY7xTb2t8E","DM7qxpmXCxE2vLu6b","rEEfxag92NJ4ZrCjg","y6QDD8QEefxZKLeZj"],"children,prev":["rEEfxag92NJ4ZrCjg","DM7qxpmXCxE2vLu6b","Z2tyyQsWY7xTb2t8E","mwb7SPre49ME24ZRP","srGzxHZamEkqFMgir","ke9wh65wDcGpm7dnB","y6QDD8QEefxZKLeZj","WDgnfcktPxFNgmz5Z"]},{"key":["Document"],"owner":"62248bb18a6b8000163a8a5d","children":["WWor6M9ZxtgsAw69z","WLJKT5A8QqWKZTwAJ"],"subBlocks":["WLJKT5A8QqWKZTwAJ","WWor6M9ZxtgsAw69z"],"portalsIn":[],"createdAt":1646562244501,"n":1,"s":1646564640221,"u":1647341562448,"_id":"R7gQTq8r5vmqsJNeL","parent":null,"rcrt":"o","typeChildren":["QETxvfjqpsmEQmidA","ov6r9tR3sTkAafnNP","ou6pTRDXtsWPSaKYg","XTaHbWN6uuew5B4Kz","6oW8TrbdyFgyiR5xE","gbMeSbzTBaBBhe4ai","cT99FNMzfjiojuNxi","nfmuKNb8zNva9Z7cd","hwFTvgNyETrhSMDmF","Qa9Lw9aqJ9SfhGRmg","5wY7T7m9FGeDMXiGz","wPmmKCDNSN5MHWgmt","QgXhCLWTtaZQGL3hE","xeu4icH3N4Drt3JSR","NPfPZr2eAbc4CvxbL"],"preMigrationTypeChildren":["QETxvfjqpsmEQmidA","ov6r9tR3sTkAafnNP","DgGsyhruH8MfmBHdx","ou6pTRDXtsWPSaKYg","fFacTzsmgaWYgik2x"]},{"key":["Status"],"owner":"62248bb18a6b8000163a8a5d","children":["zZBDGois9Luu9sGep","fk9Yp46oZBJkzkrbz","JpSgpP2j6RKf37Lmw"],"subBlocks":["JpSgpP2j6RKf37Lmw","fk9Yp46oZBJkzkrbz","zZBDGois9Luu9sGep"],"portalsIn":["R7gQTq8r5vmqsJNeL"],"createdAt":1646562244514,"s":1646564640221,"u":1647341562447,"_id":"WWor6M9ZxtgsAw69z","rcrs":"o.s","parent":"R7gQTq8r5vmqsJNeL","typeChildren":["zZBDGois9Luu9sGep","fk9Yp46oZBJkzkrbz","JpSgpP2j6RKf37Lmw"],"references":[{"q":"ujMenca6jzJDK4w8u","f":"key"},{"q":"t4mdD7F3v7SD6JCfX","f":"key"},{"q":"s5AzxmaLk5rbdnsMz","f":"key"},{"q":"Yz44zAEhArmTyjWKf","f":"key"},{"q":"AHhoHXLNSaTAALWMj","f":"key"},{"q":"5zKhzyz4WiaErmMY3","f":"key"},{"q":"c4ycFrNviFk49aZ7h","f":"key"},{"q":"QZB5QgADyddvgYwLR","f":"key"},{"q":"FjdJuv48zsgh8gCrN","f":"key"},{"q":"XXGKnqxZygB4bwAkp","f":"key"},{"q":"RtJHmzieq7x2nLEPo","f":"key"},{"q":"a7kRbbXKYzdNzPj87","f":"key"},{"q":"RRGQW9A6wYmJHqZ2q","f":"key"},{"q":"MtpJNmWyvrdniAnZk","f":"key"},{"q":"WDgnfcktPxFNgmz5Z","f":"key"},{"q":"jp5PCLPPhhAeQ7jwG","f":"key"}]},{"key":["Document"],"owner":"62248bb18a6b8000163a8a5d","children":["WWor6M9ZxtgsAw69z","WLJKT5A8QqWKZTwAJ"],"subBlocks":["WLJKT5A8QqWKZTwAJ","WWor6M9ZxtgsAw69z"],"portalsIn":[],"createdAt":1646562244501,"n":1,"s":1646564640221,"u":1647341562448,"_id":"R7gQTq8r5vmqsJNeL","parent":null,"rcrt":"o","typeChildren":["QETxvfjqpsmEQmidA","ov6r9tR3sTkAafnNP","ou6pTRDXtsWPSaKYg","XTaHbWN6uuew5B4Kz","6oW8TrbdyFgyiR5xE","gbMeSbzTBaBBhe4ai","cT99FNMzfjiojuNxi","nfmuKNb8zNva9Z7cd","hwFTvgNyETrhSMDmF","Qa9Lw9aqJ9SfhGRmg","5wY7T7m9FGeDMXiGz","wPmmKCDNSN5MHWgmt","QgXhCLWTtaZQGL3hE","xeu4icH3N4Drt3JSR","NPfPZr2eAbc4CvxbL"],"preMigrationTypeChildren":["QETxvfjqpsmEQmidA","ov6r9tR3sTkAafnNP","DgGsyhruH8MfmBHdx","ou6pTRDXtsWPSaKYg","fFacTzsmgaWYgik2x"]},{"key":["Status"],"owner":"62248bb18a6b8000163a8a5d","children":["zZBDGois9Luu9sGep","fk9Yp46oZBJkzkrbz","JpSgpP2j6RKf37Lmw"],"subBlocks":["JpSgpP2j6RKf37Lmw","fk9Yp46oZBJkzkrbz","zZBDGois9Luu9sGep"],"portalsIn":["R7gQTq8r5vmqsJNeL"],"createdAt":1646562244514,"s":1646564640221,"u":1647341562447,"_id":"WWor6M9ZxtgsAw69z","rcrs":"o.s","parent":"R7gQTq8r5vmqsJNeL","typeChildren":["zZBDGois9Luu9sGep","fk9Yp46oZBJkzkrbz","JpSgpP2j6RKf37Lmw"],"references":[{"q":"ujMenca6jzJDK4w8u","f":"key"},{"q":"t4mdD7F3v7SD6JCfX","f":"key"},{"q":"s5AzxmaLk5rbdnsMz","f":"key"},{"q":"Yz44zAEhArmTyjWKf","f":"key"},{"q":"AHhoHXLNSaTAALWMj","f":"key"},{"q":"5zKhzyz4WiaErmMY3","f":"key"},{"q":"c4ycFrNviFk49aZ7h","f":"key"},{"q":"QZB5QgADyddvgYwLR","f":"key"},{"q":"FjdJuv48zsgh8gCrN","f":"key"},{"q":"XXGKnqxZygB4bwAkp","f":"key"},{"q":"RtJHmzieq7x2nLEPo","f":"key"},{"q":"a7kRbbXKYzdNzPj87","f":"key"},{"q":"RRGQW9A6wYmJHqZ2q","f":"key"},{"q":"MtpJNmWyvrdniAnZk","f":"key"},{"q":"WDgnfcktPxFNgmz5Z","f":"key"},{"q":"jp5PCLPPhhAeQ7jwG","f":"key"}]},{"key":["Draft"],"owner":"62248bb18a6b8000163a8a5d","children":[],"subBlocks":[],"portalsIn":["WWor6M9ZxtgsAw69z"],"createdAt":1646562244526,"s":1646564640221,"u":1647341562448,"_id":"fk9Yp46oZBJkzkrbz","rcre":"o.s.Draft","typeParents":["WWor6M9ZxtgsAw69z"],"excludedTypeParents":[],"parent":"WWor6M9ZxtgsAw69z","references":[{"q":"3WDZR4Ly5vmSCstpN","f":"key"},{"q":"ujMenca6jzJDK4w8u","f":"value"},{"q":"t4mdD7F3v7SD6JCfX","f":"value"},{"q":"s5AzxmaLk5rbdnsMz","f":"value"},{"q":"Yz44zAEhArmTyjWKf","f":"value"},{"q":"AHhoHXLNSaTAALWMj","f":"value"},{"q":"5zKhzyz4WiaErmMY3","f":"value"},{"q":"c4ycFrNviFk49aZ7h","f":"value"},{"q":"QZB5QgADyddvgYwLR","f":"value"},{"q":"FjdJuv48zsgh8gCrN","f":"value"},{"q":"XXGKnqxZygB4bwAkp","f":"value"},{"q":"RtJHmzieq7x2nLEPo","f":"value"},{"q":"a7kRbbXKYzdNzPj87","f":"value"},{"q":"RRGQW9A6wYmJHqZ2q","f":"value"},{"q":"MtpJNmWyvrdniAnZk","f":"value"},{"q":"WDgnfcktPxFNgmz5Z","f":"value"},{"q":"jp5PCLPPhhAeQ7jwG","f":"value"}],"rsp":["3WDZR4Ly5vmSCstpN"]},{"key":[{"i":"q","_id":"WWor6M9ZxtgsAw69z"}],"owner":"62248bb18a6b8000163a8a5d","children":[],"subBlocks":[],"portalsIn":[],"createdAt":1647341234901,"u":1647349032742,"_id":"WDgnfcktPxFNgmz5Z","parent":"xeu4icH3N4Drt3JSR","rcrp":"o.s","value":[{"i":"q","_id":"fk9Yp46oZBJkzkrbz"}],"type":2,"forget":true}]}